Metadata-Version: 2.4
Name: mlx-embeddings
Version: 0.0.4
Summary: MLX-Embeddings is a package for running Vision and Language Embedding models locally on your Mac using MLX.
Author-email: Prince Canuma <prince.gdt@gmail.com>
License: GNU General Public License v3
Project-URL: Homepage, https://github.com/Blaizzy/mlx-embeddings
Keywords: mlx-embeddings
Classifier: Intended Audience :: Developers
Classifier: License :: OSI Approved :: GNU General Public License v3 (GPLv3)
Classifier: Natural Language :: English
Classifier: Programming Language :: Python :: 3.8
Classifier: Programming Language :: Python :: 3.9
Classifier: Programming Language :: Python :: 3.10
Classifier: Programming Language :: Python :: 3.11
Classifier: Programming Language :: Python :: 3.12
Requires-Python: >=3.8
License-File: LICENSE
License-File: AUTHORS.rst
Requires-Dist: mlx>=0.16.3
Requires-Dist: mlx-vlm>=0.1.21
Requires-Dist: transformers[sentencepiece]>=4.44.0
Requires-Dist: huggingface-hub>=0.25.1
Provides-Extra: all
Requires-Dist: mlx-embeddings[extra]; extra == "all"
Provides-Extra: extra
Requires-Dist: pandas; extra == "extra"
Dynamic: license-file
